xrobot/AddModule.py
xrobot/GenerateMain.py
xrobot/InitModule.py
xrobot/ModuleCreator.py
xrobot/ModuleParser.py
xrobot/SourceManager.py
xrobot/XRobotSetup.py
xrobot/__init__.py
xrobot-0.2.6.dist-info/LICENSE
xrobot-0.2.6.dist-info/METADATA
xrobot-0.2.6.dist-info/WHEEL
xrobot-0.2.6.dist-info/entry_points.txt
xrobot-0.2.6.dist-info/top_level.txt
xrobot-0.2.6.dist-info/RECORD
