Metadata-Version: 2.1
Name: xrobot
Version: 0.2.6
Summary: A lightweight application framework for robot module management, lifecycle control, and hardware abstraction.
Author-email: Xiao <2592509183@qq.com>
Maintainer-email: Xiao <2592509183@qq.com>
License: Apache-2.0
Project-URL: Homepage, https://github.com/xrobot-org
Project-URL: Documentation, https://xrobot-org.github.io
Project-URL: Repository, https://github.com/xrobot-org/XRobot
Project-URL: Bug Tracker, https://github.com/xrobot-org/XRobot/issues
Keywords: code generation,embedded systems,automation
Classifier: Development Status :: 3 - Alpha
Classifier: Programming Language :: Python :: 3
Classifier: License :: OSI Approved :: Apache Software License
Classifier: Operating System :: OS Independent
Requires-Python: >=3.8
License-File: LICENSE
Requires-Dist: argparse
Requires-Dist: pyyaml
Requires-Dist: requests
Provides-Extra: cli
Requires-Dist: rich; extra == "cli"
Requires-Dist: click; extra == "cli"
